{
    "2026-04-06": {
        "condition": "Mostly Cloudy",
        "is_raining": false,
        "is_storming": false
    },
    "2026-04-07": {
        "condition": "Sunny",
        "is_raining": false,
        "is_storming": false
    },
    "2026-04-08": {
        "condition": "Partly Sunny",
        "is_raining": false,
        "is_storming": false
    },
    "2026-04-09": {
        "condition": "Mostly Sunny",
        "is_raining": false,
        "is_storming": false
    },
    "2026-04-10": {
        "condition": "Mostly Sunny",
        "is_raining": false,
        "is_storming": false
    },
    "2026-04-11": {
        "condition": "Sunny",
        "is_raining": false,
        "is_storming": false
    },
    "2026-04-12": {
        "condition": "Mostly Sunny",
        "is_raining": false,
        "is_storming": false
    }
}