{
    "2026-03-19": {
        "condition": "Partly Cloudy",
        "is_raining": false,
        "is_storming": false
    },
    "2026-03-20": {
        "condition": "Sunny",
        "is_raining": false,
        "is_storming": false
    },
    "2026-03-21": {
        "condition": "Sunny",
        "is_raining": false,
        "is_storming": false
    },
    "2026-03-22": {
        "condition": "Sunny",
        "is_raining": false,
        "is_storming": false
    },
    "2026-03-23": {
        "condition": "Mostly Sunny",
        "is_raining": false,
        "is_storming": false
    },
    "2026-03-24": {
        "condition": "Partly Sunny",
        "is_raining": false,
        "is_storming": false
    },
    "2026-03-25": {
        "condition": "Mostly Sunny",
        "is_raining": false,
        "is_storming": false
    }
}